LICENSE.md
MANIFEST.in
README.rst
pyproject.toml
requirements.core.txt
requirements.txt
setup.py
core_module_periodic_table_app/__init__.py
core_module_periodic_table_app/urls.py
core_module_periodic_table_app/views.py
core_module_periodic_table_app.egg-info/PKG-INFO
core_module_periodic_table_app.egg-info/SOURCES.txt
core_module_periodic_table_app.egg-info/dependency_links.txt
core_module_periodic_table_app.egg-info/requires.txt
core_module_periodic_table_app.egg-info/top_level.txt
core_module_periodic_table_app/static/core_module_periodic_table_app/css/periodic.css
core_module_periodic_table_app/static/core_module_periodic_table_app/js/periodic.js
core_module_periodic_table_app/templates/core_module_periodic_table_app/periodic.html
core_module_periodic_table_app/templates/core_module_periodic_table_app/periodic_simple.html
tests/__init__.py
tests/test_settings.py
tests/test_unit_views.py