Metadata-Version: 2.1
Name: core-module-periodic-table-app
Version: 2.19.0
Summary: Periodic table module for the parser core project
Home-page: https://github.com/usnistgov/core_module_periodic_table_app
Author: NIST IT Lab
Author-email: itl_inquiries@nist.gov
License-File: LICENSE.md
